pints/__init__.py
pints/_version.py
pints/calling_engine.py
pints/extension_engine.py
pints/io_engine.py
pints/qc_engine.py
pints/stats_engine.py
pypints-1.2.1.data/scripts/pints_boundary_extender
pypints-1.2.1.data/scripts/pints_caller
pypints-1.2.1.data/scripts/pints_counter
pypints-1.2.1.data/scripts/pints_normalizer
pypints-1.2.1.data/scripts/pints_sample_qc
pypints-1.2.1.data/scripts/pints_visualizer
pypints-1.2.1.dist-info/licenses/LICENSE
pypints-1.2.1.dist-info/METADATA
pypints-1.2.1.dist-info/WHEEL
pypints-1.2.1.dist-info/top_level.txt
pypints-1.2.1.dist-info/RECORD
