Metadata-Version: 2.4
Name: pyPINTS
Version: 1.2.1
Summary: Peak Identifier for Nascent Transcripts Starts (PINTS)
Home-page: https://pints.yulab.org
Author: Li Yao
Author-email: regulatorygenome@gmail.com
License: GPL
License-File: LICENSE
Requires-Dist: numpy>=1.19.2
Requires-Dist: pandas>=1.1.5
Requires-Dist: scipy>=1.5.2
Requires-Dist: pysam>=0.16.0.1
Requires-Dist: requests
Requires-Dist: pybedtools>=0.8.1
Requires-Dist: statsmodels>=0.12.1
Requires-Dist: pyBigWig
Requires-Dist: biopython
Requires-Dist: matplotlib
Dynamic: author
Dynamic: author-email
Dynamic: description
Dynamic: description-content-type
Dynamic: home-page
Dynamic: license
Dynamic: license-file
Dynamic: requires-dist
Dynamic: summary
